{
  "values": {
    "modern_industrialization:capacitor": {
      "components": [
        {
          "color": "#A9A9A9",
          "italic": false,
          "translate": "text.modern_industrialization.HasBetterYieldAssemblerRecipe"
        }
      ]
    },
    "modern_industrialization:inductor": {
      "components": [
        {
          "color": "#A9A9A9",
          "italic": false,
          "translate": "text.modern_industrialization.HasBetterYieldAssemblerRecipe"
        }
      ]
    },
    "modern_industrialization:resistor": {
      "components": [
        {
          "color": "#A9A9A9",
          "italic": false,
          "translate": "text.modern_industrialization.HasBetterYieldAssemblerRecipe"
        }
      ]
    }
  }
}